{
  "participant_id": "U0016",
  "sessions": [
    {
      "session_id": "637c07b0",
      "first_accessed_at": "2026-06-20T16:30:44.393575",
      "last_accessed_at": "2026-06-20T16:31:16.546188",
      "access_count": 3,
      "source": "qr_access"
    },
    {
      "session_id": "f6348c43",
      "first_accessed_at": "2026-06-20T16:32:06.688220",
      "last_accessed_at": "2026-06-20T16:32:06.688220",
      "access_count": 1,
      "source": "qr_access"
    },
    {
      "session_id": "7d97580b",
      "first_accessed_at": "2026-06-20T16:34:56.299774",
      "last_accessed_at": "2026-06-20T16:34:56.299774",
      "access_count": 1,
      "source": "qr_access"
    },
    {
      "session_id": "4f711a23",
      "first_accessed_at": "2026-06-20T16:42:04.215366",
      "last_accessed_at": "2026-06-20T16:42:16.201123",
      "access_count": 2,
      "source": "survey_submission"
    },
    {
      "session_id": "5b10b7e1",
      "first_accessed_at": "2026-06-20T16:43:00.304382",
      "last_accessed_at": "2026-06-20T16:43:00.304382",
      "access_count": 1,
      "source": "qr_access"
    },
    {
      "session_id": "8bf93d39",
      "first_accessed_at": "2026-06-20T16:50:53.615719",
      "last_accessed_at": "2026-06-20T16:50:53.615719",
      "access_count": 1,
      "source": "qr_access"
    }
  ],
  "device_identifier": "c9416edb-8611-470c-a2b5-73efa3bc90fb",
  "last_session_id": "8bf93d39",
  "updated_at": "2026-06-20T16:50:53.615719"
}
